{"GlobalPropertiesHash":"q++2Dr7dYUuljsAI+QGcxQgwZaG5yLG8CpthJP5e7Vs=","FingerprintPatternsHash":"gq3WsqcKBUGTSNle7RKKyXRIwh7M8ccEqOqYvIzoM04=","PropertyOverridesHash":"8ZRc1sGeVrPBx4lD717BgRaQekyh78QKV9SKsdt638U=","InputHashes":["P6Arn4BdhjAn8W\u002BYxfwpAMUt8aoJKUqtYtszSUyVF7A=","R430jBSNBFYDe9iFY7KNxQdez0E8e/10LYsXFCBZIQA=","mIus7mM/\u002BlFPxywV6/FKENByBxCiR9K6tfOkX5pcBzg=","kdHXyGFuDK3aP6OO3yYXAGTRl/yDOFQ8pKrscwPsKyI=","bt6VL0v\u002BvUW1Lq2zrr2OCyJKvgkPQnlj6e4ACEqIgFg=","KQQmN95cpeaeofjDkcmJLd2KjjopHcuSv3LIrPJixuM=","oj0R7jmyF/kVTKy8ZfMVOe9alKev6k4EcqyifCUXuBs="],"CachedAssets":{"P6Arn4BdhjAn8W\u002BYxfwpAMUt8aoJKUqtYtszSUyVF7A=":{"Identity":"C:\\Users\\t-nfatema\\OneDrive - Microsoft\\Desktop\\push-notif-old-og\\wwwroot\\frontend.html","SourceId":"push_notif","SourceType":"Discovered","ContentRoot":"C:\\Users\\t-nfatema\\OneDrive - Microsoft\\Desktop\\push-notif-old-og\\wwwroot\\","BasePath":"_content/push_notif","RelativePath":"frontend#[.{fingerprint}]?.html","AssetKind":"All","AssetMode":"All","AssetRole":"Primary","AssetMergeBehavior":null,"AssetMergeSource":"","RelatedAsset":null,"AssetTraitName":null,"AssetTraitValue":null,"Fingerprint":"016d311c91","Integrity":"xPY3Azagw/19vULHADs2diQ60Rk5ZeJrtxSUNQl/jHQ=","CopyToOutputDirectory":"Never","CopyToPublishDirectory":"PreserveNewest","OriginalItemSpec":"wwwroot\\frontend.html","FileLength":311,"LastWriteTime":"2025-06-16T08:29:39.8443294+00:00"},"R430jBSNBFYDe9iFY7KNxQdez0E8e/10LYsXFCBZIQA=":{"Identity":"C:\\Users\\t-nfatema\\OneDrive - Microsoft\\Desktop\\push-notif-old-og\\wwwroot\\script.js","SourceId":"push_notif","SourceType":"Discovered","ContentRoot":"C:\\Users\\t-nfatema\\OneDrive - Microsoft\\Desktop\\push-notif-old-og\\wwwroot\\","BasePath":"_content/push_notif","RelativePath":"script#[.{fingerprint}]?.js","AssetKind":"All","AssetMode":"All","AssetRole":"Primary","AssetMergeBehavior":null,"AssetMergeSource":"","RelatedAsset":null,"AssetTraitName":null,"AssetTraitValue":null,"Fingerprint":"qtnh3hmwhk","Integrity":"3rmyV2dKsU41b3pmoYHFu95s8SUIA\u002BbMqi1tU7S/0tU=","CopyToOutputDirectory":"Never","CopyToPublishDirectory":"PreserveNewest","OriginalItemSpec":"wwwroot\\script.js","FileLength":2798,"LastWriteTime":"2025-07-02T11:23:43.9395966+00:00"},"mIus7mM/\u002BlFPxywV6/FKENByBxCiR9K6tfOkX5pcBzg=":{"Identity":"C:\\Users\\t-nfatema\\OneDrive - Microsoft\\Desktop\\push-notif-old-og\\wwwroot\\service-worker.js","SourceId":"push_notif","SourceType":"Discovered","ContentRoot":"C:\\Users\\t-nfatema\\OneDrive - Microsoft\\Desktop\\push-notif-old-og\\wwwroot\\","BasePath":"_content/push_notif","RelativePath":"service-worker#[.{fingerprint}]?.js","AssetKind":"All","AssetMode":"All","AssetRole":"Primary","AssetMergeBehavior":null,"AssetMergeSource":"","RelatedAsset":null,"AssetTraitName":null,"AssetTraitValue":null,"Fingerprint":"73t46gufig","Integrity":"QxKDvVBa9s84rbeRHu0Zh2v4rfQm5fKSgnAVDejdGNQ=","CopyToOutputDirectory":"Never","CopyToPublishDirectory":"PreserveNewest","OriginalItemSpec":"wwwroot\\service-worker.js","FileLength":5149,"LastWriteTime":"2025-07-03T06:17:16.3616558+00:00"}},"CachedCopyCandidates":{}}